just_storage/__init__.py
just_storage/client.py
just_storage/exceptions.py
just_storage/models.py
just_storage/utils.py
just_storage-0.1.1.dist-info/METADATA
just_storage-0.1.1.dist-info/WHEEL
just_storage-0.1.1.dist-info/licenses/LICENSE
just_storage-0.1.1.dist-info/RECORD
