Metadata-Version: 2.4
Name: just-storage
Version: 0.1.1
Summary: Python SDK for JustStorage object storage service
Project-URL: Homepage, https://github.com/Glowing-Pixels-UG/just-storage-python-sdk
Project-URL: Documentation, https://github.com/Glowing-Pixels-UG/just-storage-python-sdk#readme
Project-URL: Repository, https://github.com/Glowing-Pixels-UG/just-storage-python-sdk
Project-URL: Issues, https://github.com/Glowing-Pixels-UG/just-storage-python-sdk/issues
Author-email: Glowing Pixels UG <hello@glpx.pro>
License: MIT
License-File: LICENSE
Keywords: content-addressable,object-storage,sdk,storage
Classifier: Development Status :: 3 - Alpha
Classifier: Intended Audience :: Developers
Classifier: License :: OSI Approved :: MIT License
Classifier: Programming Language :: Python :: 3
Classifier: Programming Language :: Python :: 3.9
Classifier: Programming Language :: Python :: 3.10
Classifier: Programming Language :: Python :: 3.11
Classifier: Programming Language :: Python :: 3.12
Classifier: Topic :: Software Development :: Libraries :: Python Modules
Classifier: Topic :: System :: Archiving
Requires-Python: >=3.9
Requires-Dist: requests>=2.31.0
Requires-Dist: urllib3>=2.0.0
Provides-Extra: dev
Requires-Dist: black>=23.0.0; extra == 'dev'
Requires-Dist: mypy>=1.5.0; extra == 'dev'
Requires-Dist: pytest-cov>=4.1.0; extra == 'dev'
Requires-Dist: pytest>=7.4.0; extra == 'dev'
Requires-Dist: ruff>=0.1.0; extra == 'dev'
